blov_utils/__init__.py
blov_utils/aws_s3.py
blov_utils/cloudinary.py
blov_utils/general.py
blov_utils/google_img.py
blov_utils/google_nlp.py
blov_utils/ibm_watson_nlp.py
blov_utils/image_io.py
blov_utils/io.py
blov_utils/log.py
blov_utils/mongo_db.py
blov_utils/opensearch.py
blov_utils/search_engine.py
blov_utils/twitter.py
blov_utils/vid.py
blov_utils/web.py
blov_utils-0.0.2.dist-info/LICENSE.txt
blov_utils-0.0.2.dist-info/METADATA
blov_utils-0.0.2.dist-info/WHEEL
blov_utils-0.0.2.dist-info/top_level.txt
blov_utils-0.0.2.dist-info/RECORD
