Metadata-Version: 2.1
Name: blov-utils
Version: 0.0.2
Summary: This repo contains the utility functions that would typically be used across all the other functions.
Author: Bloverse
Author-email: ukeme.wilson@bloverse.com
Classifier: Programming Language :: Python :: 3
Classifier: License :: OSI Approved :: MIT License
Classifier: Operating System :: OS Independent
Requires-Python: >=3.6
License-File: LICENSE.txt
